<?xml version="1.0" encoding="ISO-8859-1"?>
<panel name="pnlStepSelectClients"  columns="1" bottom="5"
	columns="1" gap="10" left="5" right="5" top="10" weightx="1" weighty="1">
	
	<panel columns="1" gap="5" weightx="1" weighty="1">
		<label font="20 Bold" text="Add a Client" />
		<separator/>
		
		<panel weightx="1" bottom="5" gap="5" top="5">
			<button type="link" text="Select service" />
			<label text=" &gt; " />
			<button type="link" text="Targeted Savings" />
			<label text=" &gt; " />
			<button type="link" text="Select Client" />
			<label text=" &gt; " />
			<button type="link" text="Creating Settings" />
			<label text=" &gt; " />
			<label text="Review" />
		</panel>
		<label text="You have selected the following clients:" />
		<panel columns="1" gap="5" right="10" weightx="1" weighty="1">
			<table weightx="1" weighty="1">
				<header>
					<column text="Select" />
					<column text="Name" />
					<column text="Phone" />
					<column text="Account" />
				</header>
			</table>

			<label text="To save:" />
			<label text="Starting on: " />
			<label text="Ending On:" />
		</panel>
	</panel>
	<panel gap="5" halign="right" weightx="1">
		<button action="previous" icon="/icons/left.png" name="btnPrevious"
			text="Previous" />
		<panel weightx="1" />
		<button action="create" icon="/icons/add.png" name="btnCreate"
			text="Create" />
	</panel>
</panel>